chap2_gatelevel_greater_than/eq1.sv
// 1-bit equality comparator with gate-level modeling
module eq1 (
    //IO declaration
    input logic i0,i1,
    output logic eq
);

    //signal declaration
    logic p0, p1;

    //combinational logic
    assign eq = p0 | p1;
    assign p0 = ~i0 & ~i1;
    assign p1 = i0 & i1;
endmodule

chap2_gatelevel_greater_than/greater_than_2bit.sv
// checks if 2-bit input i0 is greater than i1
module greater_than_2bit (
    input logic [1:0] i0, i1,
    output logic gt
);
    logic msb_gt, lsb_gt, msb_eq;

    // check if msb is equal
    eq1 eq1_inst (
        .i0(i0[1]),
        .i1(i1[1]),
        .eq(msb_eq)
    );
    // MSB greater than
    assign msb_gt = i0[1] & ~i1[1];
    // LSB greater than
    assign lsb_gt = msb_eq & i0[0] & ~i1[0];
    // final output
    assign gt = msb_gt | lsb_gt;

endmodule

chap2_greater_than/eq2.sv
module eq2 (
    input logic [1:0] j0,j1,
    output logic aEqb
);
    logic e0, e1;
    assign aEqb = e0 & e1;
    eq1 bit0 (.i0(j0[0]),.i1(j1[0]),.eq(e0));
    eq1 bit1 (.i0(j0[1]),.i1(j1[1]),.eq(e1));
endmodule

chap2_gatelevel_greater_than/greater_than_4bit.sv
module greater_than_4bit (
    input logic [3:0] i0, i1,
    output logic gt
);
    logic ms2b_gt, ls2b_gt, ms2b_eq;

    assign gt = ms2b_gt | (ms2b_eq & ls2b_gt);

    eq2 eq2_inst (
        .j0(i0[3:2]),
        .j1(i1[3:2]),
        .aEqb(ms2b_eq)
    );

    greater_than_2bit gt_msb_inst (
        .i0(i0[3:2]),
        .i1(i1[3:2]),
        .gt(ms2b_gt)
    );

    greater_than_2bit gt_lsb_inst (
        .i0(i0[1:0]),
        .i1(i1[1:0]),
        .gt(ls2b_gt)
    );

endmodule

chap2_gatelevel_greater_than/greater_than_4bit_tb.sv
`timescale 1ns/1ps

module greater_than_4bit_tb;
    logic [3:0] i0, i1;
    logic test_out;

    greater_than_4bit uut
        (.i0(i0),
        .i1(i1),
        .gt(test_out)
        );
    // initial block for simulation
    initial begin
        $dumpfile("greater_than_4bit_tb.vcd");
        $dumpvars(0, greater_than_4bit_tb);

        for (int i=0; i<16; i++) begin
            for (int j=0; j<16; j++) begin
                i0 = i; i1 = j; #10;
                $display("i0=%b i1=%b gt=%b", i0, i1, test_out);
            end
        end
        $finish;
    end
endmodule

chap2_gatelevel_greater_than/greater_than_4bit_tb.vcd
$date
	Wed Sep 17 14:54:15 2025
$end
$version
	Icarus Verilog
$end
$timescale
	1ps
$end
$scope module greater_than_4bit_tb $end
$var wire 1 ! test_out $end
$var reg 4 " i0 [3:0] $end
$var reg 4 # i1 [3:0] $end
$scope module uut $end
$var wire 1 ! gt $end
$var wire 4 $ i0 [3:0] $end
$var wire 4 % i1 [3:0] $end
$var wire 1 & ms2b_gt $end
$var wire 1 ' ms2b_eq $end
$var wire 1 ( ls2b_gt $end
$scope module eq2_inst $end
$var wire 1 ' aEqb $end
$var wire 2 ) j0 [1:0] $end
$var wire 2 * j1 [1:0] $end
$var wire 1 + e1 $end
$var wire 1 , e0 $end
$scope module bit0 $end
$var wire 1 , eq $end
$var wire 1 - i0 $end
$var wire 1 . i1 $end
$var wire 1 / p0 $end
$var wire 1 0 p1 $end
$upscope $end
$scope module bit1 $end
$var wire 1 + eq $end
$var wire 1 1 i0 $end
$var wire 1 2 i1 $end
$var wire 1 3 p0 $end
$var wire 1 4 p1 $end
$upscope $end
$upscope $end
$scope module gt_lsb_inst $end
$var wire 1 ( gt $end
$var wire 2 5 i0 [1:0] $end
$var wire 2 6 i1 [1:0] $end
$var wire 1 7 lsb_gt $end
$var wire 1 8 msb_gt $end
$var wire 1 9 msb_eq $end
$scope module eq1_inst $end
$var wire 1 9 eq $end
$var wire 1 : i0 $end
$var wire 1 ; i1 $end
$var wire 1 < p0 $end
$var wire 1 = p1 $end
$upscope $end
$upscope $end
$scope module gt_msb_inst $end
$var wire 1 & gt $end
$var wire 2 > i0 [1:0] $end
$var wire 2 ? i1 [1:0] $end
$var wire 1 @ lsb_gt $end
$var wire 1 A msb_gt $end
$var wire 1 B msb_eq $end
$scope module eq1_inst $end
$var wire 1 B eq $end
$var wire 1 C i0 $end
$var wire 1 D i1 $end
$var wire 1 E p0 $end
$var wire 1 F p1 $end
$upscope $end
$upscope $end
$upscope $end
$scope begin $ivl_for_loop0 $end
$var integer 32 G i [31:0] $end
$scope begin $ivl_for_loop1 $end
$var integer 32 H j [31:0] $end
$upscope $end
$upscope $end
$upscope $end
$enddefinitions $end
$comment Show the parameter values. $end
$dumpall
$end
#0
$dumpvars
b0 H
b0 G
0F
1E
0D
0C
1B
0A
0@
b0 ?
b0 >
0=
1<
0;
0:
19
08
07
b0 6
b0 5
04
13
02
01
00
1/
0.
0-
1,
1+
b0 *
b0 )
0(
1'
0&
b0 %
b0 $
b0 #
b0 "
0!
$end
#10000
b1 6
b1 #
b1 %
b1 H
#20000
09
0<
1;
b10 6
b10 #
b10 %
b10 H
#30000
b11 6
b11 #
b11 %
b11 H
#40000
0'
0,
19
0/
1<
1.
0;
b1 *
b1 ?
b0 6
b100 #
b100 %
b100 H
#50000
b1 6
b101 #
b101 %
b101 H
#60000
09
0<
1;
b10 6
b110 #
b110 %
b110 H
#70000
b11 6
b111 #
b111 %
b111 H
#80000
1,
0+
0B
19
1/
03
0E
1<
0.
12
1D
0;
b10 *
b10 ?
b0 6
b1000 #
b1000 %
b1000 H
#90000
b1 6
b1001 #
b1001 %
b1001 H
#100000
09
0<
1;
b10 6
b1010 #
b1010 %
b1010 H
#110000
b11 6
b1011 #
b1011 %
b1011 H
#120000
0,
19
0/
1<
1.
0;
b11 *
b11 ?
b0 6
b1100 #
b1100 %
b1100 H
#130000
b1 6
b1101 #
b1101 %
b1101 H
#140000
09
0<
1;
b10 6
b1110 #
b1110 %
b1110 H
#150000
b11 6
b1111 #
b1111 %
b1111 H
#160000
1!
1(
17
1'
1,
1+
1B
19
1/
13
1E
1<
0.
02
0D
0;
b0 *
b0 ?
b0 6
b1 5
b0 #
b0 %
b1 "
b1 $
b1 G
b0 H
#170000
0!
0(
07
b1 6
b1 #
b1 %
b1 H
#180000
0!
09
0(
0<
07
1;
b10 6
b10 #
b10 %
b10 H
#190000
b11 6
b11 #
b11 %
b11 H
#200000
1(
17
0'
0,
19
0/
1<
1.
0;
b1 *
b1 ?
b0 6
b100 #
b100 %
b100 H
#210000
0(
07
b1 6
b101 #
b101 %
b101 H
#220000
09
0(
0<
07
1;
b10 6
b110 #
b110 %
b110 H
#230000
b11 6
b111 #
b111 %
b111 H
#240000
1(
17
1,
0+
0B
19
1/
03
0E
1<
0.
12
1D
0;
b10 *
b10 ?
b0 6
b1000 #
b1000 %
b1000 H
#250000
0(
07
b1 6
b1001 #
b1001 %
b1001 H
#260000
09
0(
0<
07
1;
b10 6
b1010 #
b1010 %
b1010 H
#270000
b11 6
b1011 #
b1011 %
b1011 H
#280000
1(
17
0,
19
0/
1<
1.
0;
b11 *
b11 ?
b0 6
b1100 #
b1100 %
b1100 H
#290000
0(
07
b1 6
b1101 #
b1101 %
b1101 H
#300000
09
0(
0<
07
1;
b10 6
b1110 #
b1110 %
b1110 H
#310000
b11 6
b1111 #
b1111 %
b1111 H
#320000
1!
1'
1,
1+
1B
1(
1/
13
1E
18
0.
02
0D
0;
1:
b0 *
b0 ?
b0 6
b10 5
b0 #
b0 %
b10 "
b10 $
b10 G
b0 H
#330000
b1 6
b1 #
b1 %
b1 H
#340000
0!
0(
19
08
1=
1;
b10 6
b10 #
b10 %
b10 H
#350000
b11 6
b11 #
b11 %
b11 H
#360000
0!
0'
0,
1(
0/
09
18
0=
1.
0;
b1 *
b1 ?
b0 6
b100 #
b100 %
b100 H
#370000
b1 6
b101 #
b101 %
b101 H
#380000
0(
19
08
1=
1;
b10 6
b110 #
b110 %
b110 H
#390000
b11 6
b111 #
b111 %
b111 H
#400000
1,
0+
0B
1(
1/
03
0E
09
18
0=
0.
12
1D
0;
b10 *
b10 ?
b0 6
b1000 #
b1000 %
b1000 H
#410000
b1 6
b1001 #
b1001 %
b1001 H
#420000
0(
19
08
1=
1;
b10 6
b1010 #
b1010 %
b1010 H
#430000
b11 6
b1011 #
b1011 %
b1011 H
#440000
0,
1(
0/
09
18
0=
1.
0;
b11 *
b11 ?
b0 6
b1100 #
b1100 %
b1100 H
#450000
b1 6
b1101 #
b1101 %
b1101 H
#460000
0(
19
08
1=
1;
b10 6
b1110 #
b1110 %
b1110 H
#470000
b11 6
b1111 #
b1111 %
b1111 H
#480000
1!
1'
1,
1+
1B
1(
1/
13
1E
09
18
07
0=
0.
02
0D
0;
b0 *
b0 ?
b0 6
b11 5
b0 #
b0 %
b11 "
b11 $
b11 G
b0 H
#490000
b1 6
b1 #
b1 %
b1 H
#500000
1!
17
1(
19
08
1=
1;
b10 6
b10 #
b10 %
b10 H
#510000
0!
0(
07
b11 6
b11 #
b11 %
b11 H
#520000
0!
0'
0,
1(
0/
09
18
07
0=
1.
0;
b1 *
b1 ?
b0 6
b100 #
b100 %
b100 H
#530000
b1 6
b101 #
b101 %
b101 H
#540000
17
1(
19
08
1=
1;
b10 6
b110 #
b110 %
b110 H
#550000
0(
07
b11 6
b111 #
b111 %
b111 H
#560000
1,
0+
0B
1(
1/
03
0E
09
18
07
0=
0.
12
1D
0;
b10 *
b10 ?
b0 6
b1000 #
b1000 %
b1000 H
#570000
b1 6
b1001 #
b1001 %
b1001 H
#580000
17
1(
19
08
1=
1;
b10 6
b1010 #
b1010 %
b1010 H
#590000
0(
07
b11 6
b1011 #
b1011 %
b1011 H
#600000
0,
1(
0/
09
18
07
0=
1.
0;
b11 *
b11 ?
b0 6
b1100 #
b1100 %
b1100 H
#610000
b1 6
b1101 #
b1101 %
b1101 H
#620000
17
1(
19
08
1=
1;
b10 6
b1110 #
b1110 %
b1110 H
#630000
0(
07
b11 6
b1111 #
b1111 %
b1111 H
#640000
1!
1&
1@
1+
1B
13
1E
1<
19
0=
0.
02
0D
0;
1-
0:
b0 *
b0 ?
b0 6
b1 )
b1 >
b0 5
b0 #
b0 %
b100 "
b100 $
b100 G
b0 H
#650000
b1 6
b1 #
b1 %
b1 H
#660000
09
0<
1;
b10 6
b10 #
b10 %
b10 H
#670000
b11 6
b11 #
b11 %
b11 H
#680000
0!
1'
0&
19
1,
0@
1<
10
1.
0;
b1 *
b1 ?
b0 6
b100 #
b100 %
b100 H
#690000
b1 6
b101 #
b101 %
b101 H
#700000
09
0<
1;
b10 6
b110 #
b110 %
b110 H
#710000
b11 6
b111 #
b111 %
b111 H
#720000
0!
0'
0+
0B
0&
19
0,
03
0E
0@
1<
00
0.
12
1D
0;
b10 *
b10 ?
b0 6
b1000 #
b1000 %
b1000 H
#730000
b1 6
b1001 #
b1001 %
b1001 H
#740000
09
0<
1;
b10 6
b1010 #
b1010 %
b1010 H
#750000
b11 6
b1011 #
b1011 %
b1011 H
#760000
19
1,
1<
10
1.
0;
b11 *
b11 ?
b0 6
b1100 #
b1100 %
b1100 H
#770000
b1 6
b1101 #
b1101 %
b1101 H
#780000
09
0<
1;
b10 6
b1110 #
b1110 %
b1110 H
#790000
b11 6
b1111 #
b1111 %
b1111 H
#800000
1!
1&
1(
1@
17
1+
1B
19
0,
13
1E
1<
00
0.
02
0D
0;
b0 *
b0 ?
b0 6
b1 5
b0 #
b0 %
b101 "
b101 $
b101 G
b0 H
#810000
0(
07
b1 6
b1 #
b1 %
b1 H
#820000
09
0(
0<
07
1;
b10 6
b10 #
b10 %
b10 H
#830000
b11 6
b11 #
b11 %
b11 H
#840000
1(
17
1!
1'
0&
19
1,
0@
1<
10
1.
0;
b1 *
b1 ?
b0 6
b100 #
b100 %
b100 H
#850000
0!
0(
07
b1 6
b101 #
b101 %
b101 H
#860000
0!
09
0(
0<
07
1;
b10 6
b110 #
b110 %
b110 H
#870000
b11 6
b111 #
b111 %
b111 H
#880000
1(
17
0!
0'
0+
0B
0&
19
0,
03
0E
0@
1<
00
0.
12
1D
0;
b10 *
b10 ?
b0 6
b1000 #
b1000 %
b1000 H
#890000
0(
07
b1 6
b1001 #
b1001 %
b1001 H
#900000
09
0(
0<
07
1;
b10 6
b1010 #
b1010 %
b1010 H
#910000
b11 6
b1011 #
b1011 %
b1011 H
#920000
1(
17
19
1,
1<
10
1.
0;
b11 *
b11 ?
b0 6
b1100 #
b1100 %
b1100 H
#930000
0(
07
b1 6
b1101 #
b1101 %
b1101 H
#940000
09
0(
0<
07
1;
b10 6
b1110 #
b1110 %
b1110 H
#950000
b11 6
b1111 #
b1111 %
b1111 H
#960000
1!
1&
1@
1+
1B
1(
0,
13
1E
18
00
0.
02
0D
0;
1:
b0 *
b0 ?
b0 6
b10 5
b0 #
b0 %
b110 "
b110 $
b110 G
b0 H
#970000
b1 6
b1 #
b1 %
b1 H
#980000
0(
19
08
1=
1;
b10 6
b10 #
b10 %
b10 H
#990000
b11 6
b11 #
b11 %
b11 H
#1000000
1'
0&
1(
1,
0@
09
18
10
0=
1.
0;
b1 *
b1 ?
b0 6
b100 #
b100 %
b100 H
#1010000
b1 6
b101 #
b101 %
b101 H
#1020000
0!
0(
19
08
1=
1;
b10 6
b110 #
b110 %
b110 H
#1030000
b11 6
b111 #
b111 %
b111 H
#1040000
0!
0'
0+
0B
0&
1(
0,
03
0E
0@
09
18
00
0=
0.
12
1D
0;
b10 *
b10 ?
b0 6
b1000 #
b1000 %
b1000 H
#1050000
b1 6
b1001 #
b1001 %
b1001 H
#1060000
0(
19
08
1=
1;
b10 6
b1010 #
b1010 %
b1010 H
#1070000
b11 6
b1011 #
b1011 %
b1011 H
#1080000
1(
1,
09
18
10
0=
1.
0;
b11 *
b11 ?
b0 6
b1100 #
b1100 %
b1100 H
#1090000
b1 6
b1101 #
b1101 %
b1101 H
#1100000
0(
19
08
1=
1;
b10 6
b1110 #
b1110 %
b1110 H
#1110000
b11 6
b1111 #
b1111 %
b1111 H
#1120000
1!
1&
1@
1+
1B
1(
0,
13
1E
09
18
07
00
0=
0.
02
0D
0;
b0 *
b0 ?
b0 6
b11 5
b0 #
b0 %
b111 "
b111 $
b111 G
b0 H
#1130000
b1 6
b1 #
b1 %
b1 H
#1140000
17
1(
19
08
1=
1;
b10 6
b10 #
b10 %
b10 H
#1150000
0(
07
b11 6
b11 #
b11 %
b11 H
#1160000
1'
0&
1(
1,
0@
09
18
07
10
0=
1.
0;
b1 *
b1 ?
b0 6
b100 #
b100 %
b100 H
#1170000
b1 6
b101 #
b101 %
b101 H
#1180000
1!
17
1(
19
08
1=
1;
b10 6
b110 #
b110 %
b110 H
#1190000
0!
0(
07
b11 6
b111 #
b111 %
b111 H
#1200000
0!
0'
0+
0B
0&
1(
0,
03
0E
0@
09
18
07
00
0=
0.
12
1D
0;
b10 *
b10 ?
b0 6
b1000 #
b1000 %
b1000 H
#1210000
b1 6
b1001 #
b1001 %
b1001 H
#1220000
17
1(
19
08
1=
1;
b10 6
b1010 #
b1010 %
b1010 H
#1230000
0(
07
b11 6
b1011 #
b1011 %
b1011 H
#1240000
1(
1,
09
18
07
10
0=
1.
0;
b11 *
b11 ?
b0 6
b1100 #
b1100 %
b1100 H
#1250000
b1 6
b1101 #
b1101 %
b1101 H
#1260000
17
1(
19
08
1=
1;
b10 6
b1110 #
b1110 %
b1110 H
#1270000
0(
07
b11 6
b1111 #
b1111 %
b1111 H
#1280000
1!
1&
1A
1/
1,
1<
19
00
0=
0.
02
0D
0;
0-
11
1C
0:
b0 *
b0 ?
b0 6
b10 )
b10 >
b0 5
b0 #
b0 %
b1000 "
b1000 $
b1000 G
b0 H
#1290000
b1 6
b1 #
b1 %
b1 H
#1300000
09
0<
1;
b10 6
b10 #
b10 %
b10 H
#1310000
b11 6
b11 #
b11 %
b11 H
#1320000
0,
19
0/
1<
1.
0;
b1 *
b1 ?
b0 6
b100 #
b100 %
b100 H
#1330000
b1 6
b101 #
b101 %
b101 H
#1340000
09
0<
1;
b10 6
b110 #
b110 %
b110 H
#1350000
b11 6
b111 #
b111 %
b111 H
#1360000
1'
0!
1,
0&
19
1/
1+
1B
0A
1<
14
1F
0.
12
1D
0;
b10 *
b10 ?
b0 6
b1000 #
b1000 %
b1000 H
#1370000
b1 6
b1001 #
b1001 %
b1001 H
#1380000
09
0<
1;
b10 6
b1010 #
b1010 %
b1010 H
#1390000
b11 6
b1011 #
b1011 %
b1011 H
#1400000
0'
0,
19
0/
1<
1.
0;
b11 *
b11 ?
b0 6
b1100 #
b1100 %
b1100 H
#1410000
b1 6
b1101 #
b1101 %
b1101 H
#1420000
09
0<
1;
b10 6
b1110 #
b1110 %
b1110 H
#1430000
b11 6
b1111 #
b1111 %
b1111 H
#1440000
1(
17
1!
1,
1&
19
1/
0+
0B
1A
1<
04
0F
0.
02
0D
0;
b0 *
b0 ?
b0 6
b1 5
b0 #
b0 %
b1001 "
b1001 $
b1001 G
b0 H
#1450000
0(
07
b1 6
b1 #
b1 %
b1 H
#1460000
09
0(
0<
07
1;
b10 6
b10 #
b10 %
b10 H
#1470000
b11 6
b11 #
b11 %
b11 H
#1480000
1(
17
0,
19
0/
1<
1.
0;
b1 *
b1 ?
b0 6
b100 #
b100 %
b100 H
#1490000
0(
07
b1 6
b101 #
b101 %
b101 H
#1500000
09
0(
0<
07
1;
b10 6
b110 #
b110 %
b110 H
#1510000
b11 6
b111 #
b111 %
b111 H
#1520000
1(
17
1'
1!
1,
0&
19
1/
1+
1B
0A
1<
14
1F
0.
12
1D
0;
b10 *
b10 ?
b0 6
b1000 #
b1000 %
b1000 H
#1530000
0!
0(
07
b1 6
b1001 #
b1001 %
b1001 H
#1540000
0!
09
0(
0<
07
1;
b10 6
b1010 #
b1010 %
b1010 H
#1550000
b11 6
b1011 #
b1011 %
b1011 H
#1560000
1(
17
0'
0,
19
0/
1<
1.
0;
b11 *
b11 ?
b0 6
b1100 #
b1100 %
b1100 H
#1570000
0(
07
b1 6
b1101 #
b1101 %
b1101 H
#1580000
09
0(
0<
07
1;
b10 6
b1110 #
b1110 %
b1110 H
#1590000
b11 6
b1111 #
b1111 %
b1111 H
#1600000
1!
1,
1&
1(
1/
0+
0B
1A
18
04
0F
0.
02
0D
0;
1:
b0 *
b0 ?
b0 6
b10 5
b0 #
b0 %
b1010 "
b1010 $
b1010 G
b0 H
#1610000
b1 6
b1 #
b1 %
b1 H
#1620000
0(
19
08
1=
1;
b10 6
b10 #
b10 %
b10 H
#1630000
b11 6
b11 #
b11 %
b11 H
#1640000
0,
1(
0/
09
18
0=
1.
0;
b1 *
b1 ?
b0 6
b100 #
b100 %
b100 H
#1650000
b1 6
b101 #
b101 %
b101 H
#1660000
0(
19
08
1=
1;
b10 6
b110 #
b110 %
b110 H
#1670000
b11 6
b111 #
b111 %
b111 H
#1680000
1'
1!
1,
0&
1(
1/
1+
1B
0A
09
18
14
1F
0=
0.
12
1D
0;
b10 *
b10 ?
b0 6
b1000 #
b1000 %
b1000 H
#1690000
b1 6
b1001 #
b1001 %
b1001 H
#1700000
0!
0(
19
08
1=
1;
b10 6
b1010 #
b1010 %
b1010 H
#1710000
b11 6
b1011 #
b1011 %
b1011 H
#1720000
0!
0'
0,
1(
0/
09
18
0=
1.
0;
b11 *
b11 ?
b0 6
b1100 #
b1100 %
b1100 H
#1730000
b1 6
b1101 #
b1101 %
b1101 H
#1740000
0(
19
08
1=
1;
b10 6
b1110 #
b1110 %
b1110 H
#1750000
b11 6
b1111 #
b1111 %
b1111 H
#1760000
1!
1,
1&
1(
1/
0+
0B
1A
09
18
07
04
0F
0=
0.
02
0D
0;
b0 *
b0 ?
b0 6
b11 5
b0 #
b0 %
b1011 "
b1011 $
b1011 G
b0 H
#1770000
b1 6
b1 #
b1 %
b1 H
#1780000
17
1(
19
08
1=
1;
b10 6
b10 #
b10 %
b10 H
#1790000
0(
07
b11 6
b11 #
b11 %
b11 H
#1800000
0,
1(
0/
09
18
07
0=
1.
0;
b1 *
b1 ?
b0 6
b100 #
b100 %
b100 H
#1810000
b1 6
b101 #
b101 %
b101 H
#1820000
17
1(
19
08
1=
1;
b10 6
b110 #
b110 %
b110 H
#1830000
0(
07
b11 6
b111 #
b111 %
b111 H
#1840000
1'
1!
1,
0&
1(
1/
1+
1B
0A
09
18
07
14
1F
0=
0.
12
1D
0;
b10 *
b10 ?
b0 6
b1000 #
b1000 %
b1000 H
#1850000
b1 6
b1001 #
b1001 %
b1001 H
#1860000
1!
17
1(
19
08
1=
1;
b10 6
b1010 #
b1010 %
b1010 H
#1870000
0!
0(
07
b11 6
b1011 #
b1011 %
b1011 H
#1880000
0!
0'
0,
1(
0/
09
18
07
0=
1.
0;
b11 *
b11 ?
b0 6
b1100 #
b1100 %
b1100 H
#1890000
b1 6
b1101 #
b1101 %
b1101 H
#1900000
17
1(
19
08
1=
1;
b10 6
b1110 #
b1110 %
b1110 H
#1910000
0(
07
b11 6
b1111 #
b1111 %
b1111 H
#1920000
1!
1&
0+
0B
1A
0@
1<
19
04
0F
0=
0.
02
0D
0;
1-
0:
b0 *
b0 ?
b0 6
b11 )
b11 >
b0 5
b0 #
b0 %
b1100 "
b1100 $
b1100 G
b0 H
#1930000
b1 6
b1 #
b1 %
b1 H
#1940000
09
0<
1;
b10 6
b10 #
b10 %
b10 H
#1950000
b11 6
b11 #
b11 %
b11 H
#1960000
19
1,
1<
10
1.
0;
b1 *
b1 ?
b0 6
b100 #
b100 %
b100 H
#1970000
b1 6
b101 #
b101 %
b101 H
#1980000
09
0<
1;
b10 6
b110 #
b110 %
b110 H
#1990000
b11 6
b111 #
b111 %
b111 H
#2000000
1@
1!
1&
19
0,
1+
1B
0A
1<
00
14
1F
0.
12
1D
0;
b10 *
b10 ?
b0 6
b1000 #
b1000 %
b1000 H
#2010000
b1 6
b1001 #
b1001 %
b1001 H
#2020000
09
0<
1;
b10 6
b1010 #
b1010 %
b1010 H
#2030000
b11 6
b1011 #
b1011 %
b1011 H
#2040000
0!
1'
0&
19
1,
0@
1<
10
1.
0;
b11 *
b11 ?
b0 6
b1100 #
b1100 %
b1100 H
#2050000
b1 6
b1101 #
b1101 %
b1101 H
#2060000
09
0<
1;
b10 6
b1110 #
b1110 %
b1110 H
#2070000
b11 6
b1111 #
b1111 %
b1111 H
#2080000
1(
17
1!
0'
1&
19
0,
0+
0B
1A
0@
1<
00
04
0F
0.
02
0D
0;
b0 *
b0 ?
b0 6
b1 5
b0 #
b0 %
b1101 "
b1101 $
b1101 G
b0 H
#2090000
0(
07
b1 6
b1 #
b1 %
b1 H
#2100000
09
0(
0<
07
1;
b10 6
b10 #
b10 %
b10 H
#2110000
b11 6
b11 #
b11 %
b11 H
#2120000
1(
17
19
1,
1<
10
1.
0;
b1 *
b1 ?
b0 6
b100 #
b100 %
b100 H
#2130000
0(
07
b1 6
b101 #
b101 %
b101 H
#2140000
09
0(
0<
07
1;
b10 6
b110 #
b110 %
b110 H
#2150000
b11 6
b111 #
b111 %
b111 H
#2160000
1(
17
1@
1!
1&
19
0,
1+
1B
0A
1<
00
14
1F
0.
12
1D
0;
b10 *
b10 ?
b0 6
b1000 #
b1000 %
b1000 H
#2170000
0(
07
b1 6
b1001 #
b1001 %
b1001 H
#2180000
09
0(
0<
07
1;
b10 6
b1010 #
b1010 %
b1010 H
#2190000
b11 6
b1011 #
b1011 %
b1011 H
#2200000
1(
17
1!
1'
0&
19
1,
0@
1<
10
1.
0;
b11 *
b11 ?
b0 6
b1100 #
b1100 %
b1100 H
#2210000
0!
0(
07
b1 6
b1101 #
b1101 %
b1101 H
#2220000
0!
09
0(
0<
07
1;
b10 6
b1110 #
b1110 %
b1110 H
#2230000
b11 6
b1111 #
b1111 %
b1111 H
#2240000
1!
0'
1&
1(
0,
0+
0B
1A
0@
18
00
04
0F
0.
02
0D
0;
1:
b0 *
b0 ?
b0 6
b10 5
b0 #
b0 %
b1110 "
b1110 $
b1110 G
b0 H
#2250000
b1 6
b1 #
b1 %
b1 H
#2260000
0(
19
08
1=
1;
b10 6
b10 #
b10 %
b10 H
#2270000
b11 6
b11 #
b11 %
b11 H
#2280000
1(
1,
09
18
10
0=
1.
0;
b1 *
b1 ?
b0 6
b100 #
b100 %
b100 H
#2290000
b1 6
b101 #
b101 %
b101 H
#2300000
0(
19
08
1=
1;
b10 6
b110 #
b110 %
b110 H
#2310000
b11 6
b111 #
b111 %
b111 H
#2320000
1@
1!
1&
1(
0,
1+
1B
0A
09
18
00
14
1F
0=
0.
12
1D
0;
b10 *
b10 ?
b0 6
b1000 #
b1000 %
b1000 H
#2330000
b1 6
b1001 #
b1001 %
b1001 H
#2340000
0(
19
08
1=
1;
b10 6
b1010 #
b1010 %
b1010 H
#2350000
b11 6
b1011 #
b1011 %
b1011 H
#2360000
1'
0&
1(
1,
0@
09
18
10
0=
1.
0;
b11 *
b11 ?
b0 6
b1100 #
b1100 %
b1100 H
#2370000
b1 6
b1101 #
b1101 %
b1101 H
#2380000
0!
0(
19
08
1=
1;
b10 6
b1110 #
b1110 %
b1110 H
#2390000
b11 6
b1111 #
b1111 %
b1111 H
#2400000
1!
0'
1&
1(
0,
0+
0B
1A
0@
09
18
07
00
04
0F
0=
0.
02
0D
0;
b0 *
b0 ?
b0 6
b11 5
b0 #
b0 %
b1111 "
b1111 $
b1111 G
b0 H
#2410000
b1 6
b1 #
b1 %
b1 H
#2420000
17
1(
19
08
1=
1;
b10 6
b10 #
b10 %
b10 H
#2430000
0(
07
b11 6
b11 #
b11 %
b11 H
#2440000
1(
1,
09
18
07
10
0=
1.
0;
b1 *
b1 ?
b0 6
b100 #
b100 %
b100 H
#2450000
b1 6
b101 #
b101 %
b101 H
#2460000
17
1(
19
08
1=
1;
b10 6
b110 #
b110 %
b110 H
#2470000
0(
07
b11 6
b111 #
b111 %
b111 H
#2480000
1@
1!
1&
1(
0,
1+
1B
0A
09
18
07
00
14
1F
0=
0.
12
1D
0;
b10 *
b10 ?
b0 6
b1000 #
b1000 %
b1000 H
#2490000
b1 6
b1001 #
b1001 %
b1001 H
#2500000
17
1(
19
08
1=
1;
b10 6
b1010 #
b1010 %
b1010 H
#2510000
0(
07
b11 6
b1011 #
b1011 %
b1011 H
#2520000
1'
0&
1(
1,
0@
09
18
07
10
0=
1.
0;
b11 *
b11 ?
b0 6
b1100 #
b1100 %
b1100 H
#2530000
b1 6
b1101 #
b1101 %
b1101 H
#2540000
1!
17
1(
19
08
1=
1;
b10 6
b1110 #
b1110 %
b1110 H
#2550000
0!
0(
07
b11 6
b1111 #
b1111 %
b1111 H
#2560000
b10000 G
b10000 H
