chap2_gatelevel_greater_than/eq1.sv
// 1-bit equality comparator with gate-level modeling
module eq1 (
    //IO declaration
    input logic i0,i1,
    output logic eq
);

    //signal declaration
    logic p0, p1;

    //combinational logic
    assign eq = p0 | p1;
    assign p0 = ~i0 & ~i1;
    assign p1 = i0 & i1;
endmodule

chap2_gatelevel_greater_than/greater_than_2bit.sv
// checks if 2-bit input i0 is greater than i1
module greater_than_2bit (
    input logic [1:0] i0, i1,
    output logic gt
);
    logic msb_gt, lsb_gt, msb_eq;

    // check if msb is equal
    eq1 eq1_inst (
        .i0(i0[1]),
        .i1(i1[1]),
        .eq(msb_eq)
    );
    // MSB greater than
    assign msb_gt = i0[1] & ~i1[1];
    // LSB greater than
    assign lsb_gt = msb_eq & i0[0] & ~i1[0];
    // final output
    assign gt = msb_gt | lsb_gt;

endmodule

chap2_gatelevel_greater_than/greater_than_2bit_tb.sv
`timescale 1ns / 10ps

module greater_than_2bit_tb;
    logic [1:0] i0, i1;
    logic test_out;

    greater_than_2bit uut
        (.i0(i0),
        .i1(i1),
        .gt(test_out)
        );
    // initial block for simulation
    initial begin
        $dumpfile("greater_than_2bit_tb.vcd");
        $dumpvars(0, greater_than_2bit_tb);

        for (int i=0; i<4; i++) begin
            for (int j=0; j<4; j++) begin
                i0 = i; i1 = j; #10;
                $monitor("i0=%b i1=%b gt=%b", i0, i1, test_out);
            end
        end
        $finish;
    end
endmodule

chap2_greater_than/greater_than_2bit_tb.vcd
$date
	Wed Sep 17 13:02:40 2025
$end
$version
	Icarus Verilog
$end
$timescale
	10ps
$end
$scope module greater_than_2bit_tb $end
$var wire 1 ! test_out $end
$var reg 2 " i0 [1:0] $end
$var reg 2 # i1 [1:0] $end
$scope module uut $end
$var wire 1 ! gt $end
$var wire 2 $ i0 [1:0] $end
$var wire 2 % i1 [1:0] $end
$var wire 1 & lsb_gt $end
$var wire 1 ' msb_gt $end
$var wire 1 ( msb_eq $end
$scope module eq1_inst $end
$var wire 1 ( eq $end
$var wire 1 ) i0 $end
$var wire 1 * i1 $end
$var wire 1 + p0 $end
$var wire 1 , p1 $end
$upscope $end
$upscope $end
$scope begin $ivl_for_loop0 $end
$var integer 32 - i [31:0] $end
$scope begin $ivl_for_loop1 $end
$var integer 32 . j [31:0] $end
$upscope $end
$upscope $end
$upscope $end
$enddefinitions $end
$comment Show the parameter values. $end
$dumpall
$end
#0
$dumpvars
b0 .
b0 -
0,
1+
0*
0)
1(
0'
0&
b0 %
b0 $
b0 #
b0 "
0!
$end
#1000
b1 #
b1 %
b1 .
#2000
0(
0+
1*
b10 #
b10 %
b10 .
#3000
b11 #
b11 %
b11 .
#4000
1!
1&
1(
1+
0*
b0 #
b0 %
b1 "
b1 $
b1 -
b0 .
#5000
0!
0&
b1 #
b1 %
b1 .
#6000
0(
0!
0+
0&
1*
b10 #
b10 %
b10 .
#7000
b11 #
b11 %
b11 .
#8000
1!
1'
0*
1)
b0 #
b0 %
b10 "
b10 $
b10 -
b0 .
#9000
b1 #
b1 %
b1 .
#10000
0!
1(
0'
1,
1*
b10 #
b10 %
b10 .
#11000
b11 #
b11 %
b11 .
#12000
1!
0(
1'
0&
0,
0*
b0 #
b0 %
b11 "
b11 $
b11 -
b0 .
#13000
b1 #
b1 %
b1 .
#14000
1&
1!
1(
0'
1,
1*
b10 #
b10 %
b10 .
#15000
0!
0&
b11 #
b11 %
b11 .
#16000
b100 -
b100 .
