chap2_binary_decoder/binary_decoder_2to4.sv
module binary_decoder_2to4 (
    input logic [1:0] binary_in,
    input logic en,
    output logic [3:0] one_hot_out
);
    always_comb begin
        if (en) begin
            case (binary_in)
                2'b00: one_hot_out = 4'b0001;
                2'b01: one_hot_out = 4'b0010;
                2'b10: one_hot_out = 4'b0100;
                2'b11: one_hot_out = 4'b1000;
                default: one_hot_out = 4'b0000;
            endcase
        end
        else begin
            one_hot_out = 4'b0000;
        end
    end
endmodule

chap2_binary_decoder/binary_decoder_2to4_tb.sv
module binary_decoder_2to4_tb;
    logic [1:0] binary_in;
    logic en;
    logic [3:0] test_out;

    binary_decoder_2to4 uut
        (.binary_in(binary_in),
        .en(en),
        .one_hot_out(test_out)
        );
    // initial block for simulation
    initial begin
        $dumpfile("binary_decoder_2to4_tb.vcd");
        $dumpvars(0, binary_decoder_2to4_tb);
        $monitor("binary_in=%b en=%b one_hot_out=%b", binary_in, en, test_out);
        for (int i=0; i<4; i++) begin
            binary_in = i; en = 1'b1; #10;
        end
        for (int i=0; i<4; i++) begin
            binary_in = i; en = 1'b0; #10;
        end
    end
endmodule

chap2_binary_decoder/binary_decoder_2to4_tb.vcd
$date
	Wed Sep 17 15:24:33 2025
$end
$version
	Icarus Verilog
$end
$timescale
	1s
$end
$scope module binary_decoder_2to4_tb $end
$var wire 4 ! test_out [3:0] $end
$var reg 2 " binary_in [1:0] $end
$var reg 1 # en $end
$scope module uut $end
$var wire 2 $ binary_in [1:0] $end
$var wire 1 # en $end
$var reg 4 % one_hot_out [3:0] $end
$upscope $end
$scope begin $ivl_for_loop0 $end
$var integer 32 & i [31:0] $end
$upscope $end
$scope begin $ivl_for_loop1 $end
$var integer 32 ' i [31:0] $end
$upscope $end
$upscope $end
$enddefinitions $end
$comment Show the parameter values. $end
$dumpall
$end
#0
$dumpvars
b0 '
b0 &
b1 %
b0 $
1#
b0 "
b1 !
$end
#10
b10 !
b10 %
b1 "
b1 $
b1 &
#20
b100 !
b100 %
b10 "
b10 $
b10 &
#30
b1000 !
b1000 %
b11 "
b11 $
b11 &
#40
b0 !
b0 %
0#
b0 "
b0 $
b100 &
#50
b1 "
b1 $
b1 '
#60
b10 "
b10 $
b10 '
#70
b11 "
b11 $
b11 '
#80
b100 '
